[
    {
        "id":1,
        "name":"San Felipe",
        "number":"105",
        "category":"Clínicas",
        "picture":"",
        "descripction":"Lorem ...",
        "top":true
    },
    {
        "id":8,
        "name":"Migraciones",
        "number":"105",
        "category":"Estado Peruano",
        "picture":"",
        "descripction":"Lorem ...",
        "top":true
    },
    {
        "id":2,
        "name":"Ambulanias SAMU",
        "number":"106",
        "category":"Emergencia",
        "picture":"105.png",
        "descripction":"Lorem ...",
        "top":true
    },
    {
        "id":3,
        "name":"Bomberos",
        "number":"116",
        "category":"Emergencia",
        "picture":"105.png",
        "descripction":"Lorem ...",
        "top":false

    },
    {
        "id":4,
        "name":"Scotiabank",
        "number":"105",
        "category":"Banco",
        "picture":"105.png",
        "descripction":"Lorem ...",
        "top":false
    },
    {
        "id":5,
        "name":"Interbank",
        "number":"108",
        "category":"Banco",
        "picture":"105.png",
        "descripction":"Lorem ...",
        "top":false
    },
    {
        "id":6,
        "name":"Luz del Sur",
        "number":"108",
        "category":"Servicios Publicos",
        "picture":"105.png",
        "descripction":"Lorem ...",
        "top":false
    },
    {
        "id":7,
        "name":"Sedapal",
        "number":"108",
        "category":"Servicios Publicos",
        "picture":"105.png",
        "descripction":"Lorem ...",
        "top":false
    },
    {
        "id":8,
        "name":"Rimac Seguros",
        "number":"108",
        "category":"Seguros",
        "picture":"105.png",
        "descripction":"Lorem ...",
        "top":false
    }
]